leksara/__init__.py
leksara/function.py
leksara/pattern.py
leksara/version.py
leksara/core/chain.py
leksara/core/logging.py
leksara/core/presets.py
leksara/frames/cartboard.py
leksara/functions/__init__.py
leksara/functions/cleaner/__init__.py
leksara/functions/cleaner/basic.py
leksara/functions/patterns/__init__.py
leksara/functions/patterns/pii.py
leksara/functions/review/__init__.py
leksara/functions/review/advanced.py
leksara/resources/dictionary/acronym_dict.json
leksara/resources/dictionary/city_dict.json
leksara/resources/dictionary/contractions_dict.json
leksara/resources/dictionary/dictionary_README.md
leksara/resources/dictionary/dictionary_rules.json
leksara/resources/dictionary/emoji_dictionary.json
leksara/resources/dictionary/slangs_dict.json
leksara/resources/dictionary/whitelist.json
leksara/resources/regex_patterns/pii_patterns.json
leksara/resources/regex_patterns/pii_rules.json
leksara/resources/regex_patterns/rating_patterns.json
leksara/resources/regex_patterns/rating_rules.json
leksara/resources/regex_patterns/regex_README.md
leksara/resources/regex_patterns/docs/rating_guide.md
leksara/resources/regex_patterns/docs/regex_address.md
leksara/resources/stopwords/id.txt
leksara/tests/conftest.py
leksara/tests/test_cartboard_orchestrators.py
leksara/tests/test_chain.py
leksara/tests/test_cleaner_basic.py
leksara/tests/test_conftest_setup.py
leksara/tests/test_patterns_pii.py
leksara/tests/test_review_advanced.py
leksara/utils/lang.py
leksara/utils/text.py
leksara/utils/whitelist.py
leksara-0.2.2.dist-info/licenses/LICENSE
leksara-0.2.2.dist-info/METADATA
leksara-0.2.2.dist-info/WHEEL
leksara-0.2.2.dist-info/top_level.txt
leksara-0.2.2.dist-info/RECORD
