Metadata-Version: 2.4
Name: leksara
Version: 0.2.2
Summary: Library pemrosesan teks Bahasa Indonesia untuk domain e-commerce (cleaning, PII masking, review mining, pipeline).
Author: Rhendy Saragih
License: MIT
Project-URL: Homepage, https://example.com/leksara
Project-URL: Source, https://example.com/leksara/repo
Project-URL: Issues, https://example.com/leksara/issues
Project-URL: Documentation, https://example.com/leksara/docs
Keywords: nlp,indonesian,text-cleaning,ecommerce,pii,preprocessing,review-mining,normalization
Classifier: Development Status :: 2 - Pre-Alpha
Classifier: Intended Audience :: Developers
Classifier: Intended Audience :: Science/Research
Classifier: License :: OSI Approved :: MIT License
Classifier: Natural Language :: Indonesian
Classifier: Programming Language :: Python :: 3.9
Classifier: Programming Language :: Python :: 3.10
Classifier: Programming Language :: Python :: 3.11
Classifier: Programming Language :: Python :: 3.12
Classifier: Topic :: Text Processing :: Linguistic
Classifier: Topic :: Software Development :: Libraries
Requires-Python: >=3.9
License-File: LICENSE
Requires-Dist: pandas>=1.5
Requires-Dist: regex>=2022.1.18
Requires-Dist: emoji>=2.0.0
Requires-Dist: Sastrawi>=1.0.1
Provides-Extra: dev
Requires-Dist: ruff>=0.4.0; extra == "dev"
Requires-Dist: mypy>=1.8.0; extra == "dev"
Requires-Dist: pytest>=7.4; extra == "dev"
Requires-Dist: pytest-cov>=4.1; extra == "dev"
Requires-Dist: build; extra == "dev"
Requires-Dist: twine; extra == "dev"
Requires-Dist: ipykernel; extra == "dev"
Provides-Extra: docs
Requires-Dist: mkdocs; extra == "docs"
Requires-Dist: mkdocs-material; extra == "docs"
Provides-Extra: test
Requires-Dist: pytest>=7.4; extra == "test"
Requires-Dist: pytest-cov>=4.1; extra == "test"
Provides-Extra: benchmark
Requires-Dist: tqdm; extra == "benchmark"
Requires-Dist: tabulate; extra == "benchmark"
Dynamic: license-file
